MANIFEST.in
README.rst
setup.py
bio_utils/__init__.py
bio_utils.egg-info/PKG-INFO
bio_utils.egg-info/SOURCES.txt
bio_utils.egg-info/dependency_links.txt
bio_utils.egg-info/entry_points.txt
bio_utils.egg-info/not-zip-safe
bio_utils.egg-info/top_level.txt
bio_utils/blast_tools/__init__.py
bio_utils/blast_tools/blast_to_cigar.py
bio_utils/blast_tools/filter_b6_evalue.py
bio_utils/blast_tools/retrieve_query_sequences.py
bio_utils/blast_tools/retrieve_subject_sequences.py
bio_utils/iterators/__init__.py
bio_utils/iterators/b6.py
bio_utils/iterators/fasta.py
bio_utils/iterators/fastq.py
bio_utils/iterators/gff3.py
bio_utils/iterators/sam.py
bio_utils/verifiers/__init__.py
bio_utils/verifiers/b6.py
bio_utils/verifiers/binary.py
bio_utils/verifiers/fasta.py
bio_utils/verifiers/fastq.py
bio_utils/verifiers/gff3.py
bio_utils/verifiers/sam.py
bio_utils/verifiers/verify_entries.py