Metadata-Version: 1.1
Name: bio-utils
Version: 1.1.0
Summary: library of common bioinformatic tasks
Home-page: https://github.com/Brazelton-Lab/bio_utils/
Author: Alex Hyer
Author-email: theonehyer@gmail.com
License: GPLv3
Download-URL: https://github.com/Brazelton-Lab/metameta/tarball/1.1.0
Keywords: bioinformatics iterators verifiers verify iterate utilities
Platform: UNKNOWN
Classifier: Development Status :: 5 - Production/Stable
Classifier: Intended Audience :: Science/Research
Classifier: License :: OSI Approved :: GNU General Public License v3 (GPLv3)
Classifier: Natural Language :: English
Classifier: Operating System :: OS Independent
Classifier: Programming Language :: Python :: 3.6
Classifier: Topic :: Scientific/Engineering :: Bio-Informatics
Classifier: Topic :: Software Development :: Libraries :: Python Modules
